docx2python/__init__.py
docx2python/depth_collector.py
docx2python/docx_context.py
docx2python/docx_output.py
docx2python/docx_text.py
docx2python/iterators.py
docx2python/main.py
docx2python/namespace.py
docx2python/numbering_formats.py
docx2python/text_runs.py
docx2python_kryon-1.0.2.dist-info/LICENSE.txt
docx2python_kryon-1.0.2.dist-info/METADATA
docx2python_kryon-1.0.2.dist-info/WHEEL
docx2python_kryon-1.0.2.dist-info/top_level.txt
docx2python_kryon-1.0.2.dist-info/RECORD
