Metadata-Version: 2.1
Name: docx2python-kryon
Version: 1.0.2
Summary: Extract content from docx files. Edited for Kryon Studio (RPA).
Home-page: https://github.com/FabianGroeger96/docx2python
Author: Fabian Gröger
Author-email: fabian.groeger@bluewin.ch
License: UNKNOWN
Platform: UNKNOWN
Classifier: Programming Language :: Python :: 3.5
Classifier: License :: OSI Approved :: MIT License
Classifier: Operating System :: OS Independent
